{
    "display": {
        "icon": {
            "id": "minecraft:shield",
            "count": 1
        },
        "title": {
            "translate": "advancements.guarding.story.parry_this_you_casual"
        },
        "description": {
            "translate": "advancements.guarding.story.parry_this_you_casual.desc"
        },
        "hidden": true,
        "frame": "challenge"
    },
    "parent": "guarding:story/symbolic_shield",
    "criteria": {
        "killed_by_parried_arrow": {
            "trigger": "guarding:killed_by_parried_arrow",
            "conditions": {}
        }
    },
    "requirements": [["killed_by_parried_arrow"]],
    "rewards": {
        "experience": 100
    }
}
